{
  "version": "6.0",
  "nxVersion": "20.4.6",
  "pathMappings": {},
  "nxJsonPlugins": [
    {
      "name": "@nx/webpack/plugin",
      "options": {
        "buildTargetName": "build",
        "serveTargetName": "serve",
        "previewTargetName": "preview"
      }
    },
    {
      "name": "@nx/eslint/plugin",
      "options": {
        "targetName": "lint"
      }
    },
    {
      "name": "@nx/jest/plugin",
      "options": {
        "targetName": "test"
      }
    },
    {
      "name": "@nx/js/typescript",
      "options": {
        "typecheck": {
          "targetName": "typecheck"
        },
        "build": {
          "targetName": "build",
          "configName": "tsconfig.lib.json"
        }
      }
    }
  ],
  "fileMap": {
    "nonProjectFiles": [],
    "projectFileMap": {
      "my-express-api": [
        {
          "file": "apps/my-express-api/eslint.config.cjs",
          "hash": "7759795430795630113"
        },
        {
          "file": "apps/my-express-api/jest.config.ts",
          "hash": "3923302940049323941"
        },
        {
          "file": "apps/my-express-api/project.json",
          "hash": "6165743298282356474"
        },
        {
          "file": "apps/my-express-api/src/assets/.gitkeep",
          "hash": "3244421341483603138"
        },
        {
          "file": "apps/my-express-api/src/main.ts",
          "hash": "15221532221605211534",
          "deps": [
            "npm:express"
          ]
        },
        {
          "file": "apps/my-express-api/tsconfig.app.json",
          "hash": "7882563681638815931"
        },
        {
          "file": "apps/my-express-api/tsconfig.json",
          "hash": "3490524966360018312"
        },
        {
          "file": "apps/my-express-api/tsconfig.spec.json",
          "hash": "6622138706846345436"
        },
        {
          "file": "apps/my-express-api/webpack.config.js",
          "hash": "9206641348907792653",
          "deps": [
            "npm:@nx/webpack"
          ]
        }
      ],
      "lobay": [
        {
          "file": ".github/workflows/ci.yml",
          "hash": "6968453139367291536"
        },
        {
          "file": ".gitignore",
          "hash": "65001714494458486"
        },
        {
          "file": ".idea/lobay.iml",
          "hash": "13846908774985673040"
        },
        {
          "file": ".idea/material_theme_project_new.xml",
          "hash": "15689621775398881808"
        },
        {
          "file": ".idea/misc.xml",
          "hash": "13456087843525203564"
        },
        {
          "file": ".idea/modules.xml",
          "hash": "15644791202527746667"
        },
        {
          "file": ".idea/vcs.xml",
          "hash": "14600148892634157659"
        },
        {
          "file": ".idea/workspace.xml",
          "hash": "13351409663112427276"
        },
        {
          "file": ".prettierignore",
          "hash": "14688272390704683536"
        },
        {
          "file": ".prettierrc",
          "hash": "16267754514737964994"
        },
        {
          "file": "apps/lobay/.gitignore",
          "hash": "1487491545795915773"
        },
        {
          "file": "apps/lobay/.metadata",
          "hash": "6764411668264621536"
        },
        {
          "file": "apps/lobay/README.md",
          "hash": "10673631665495574986"
        },
        {
          "file": "apps/lobay/analysis_options.yaml",
          "hash": "3650987223333083373"
        },
        {
          "file": "apps/lobay/android/.gitignore",
          "hash": "7220182562130177456"
        },
        {
          "file": "apps/lobay/android/app/build.gradle",
          "hash": "5704371991924846200"
        },
        {
          "file": "apps/lobay/android/app/src/debug/AndroidManifest.xml",
          "hash": "2424010824173831934"
        },
        {
          "file": "apps/lobay/android/app/src/main/AndroidManifest.xml",
          "hash": "10932903061021073995"
        },
        {
          "file": "apps/lobay/android/app/src/main/kotlin/com/lobay/app/lobay/MainActivity.kt",
          "hash": "6984342698986002516"
        },
        {
          "file": "apps/lobay/android/app/src/main/res/drawable-v21/launch_background.xml",
          "hash": "4986171810521098768"
        },
        {
          "file": "apps/lobay/android/app/src/main/res/drawable/launch_background.xml",
          "hash": "750324681697267716"
        },
        {
          "file": "apps/lobay/android/app/src/main/res/mipmap-hdpi/ic_launcher.png",
          "hash": "17515915797888911451"
        },
        {
          "file": "apps/lobay/android/app/src/main/res/mipmap-mdpi/ic_launcher.png",
          "hash": "12758156220368008677"
        },
        {
          "file": "apps/lobay/android/app/src/main/res/mipmap-xhdpi/ic_launcher.png",
          "hash": "17821057072759496051"
        },
        {
          "file": "apps/lobay/android/app/src/main/res/mipmap-xxhdpi/ic_launcher.png",
          "hash": "13291011583500627668"
        },
        {
          "file": "apps/lobay/android/app/src/main/res/mipmap-xxxhdpi/ic_launcher.png",
          "hash": "10239208634629745166"
        },
        {
          "file": "apps/lobay/android/app/src/main/res/values-night/styles.xml",
          "hash": "1856035890191000928"
        },
        {
          "file": "apps/lobay/android/app/src/main/res/values/styles.xml",
          "hash": "315751654984603465"
        },
        {
          "file": "apps/lobay/android/app/src/profile/AndroidManifest.xml",
          "hash": "2424010824173831934"
        },
        {
          "file": "apps/lobay/android/build.gradle",
          "hash": "2830036735361506935"
        },
        {
          "file": "apps/lobay/android/gradle.properties",
          "hash": "1264519489710196683"
        },
        {
          "file": "apps/lobay/android/gradle/wrapper/gradle-wrapper.properties",
          "hash": "3833905432515876602"
        },
        {
          "file": "apps/lobay/android/settings.gradle",
          "hash": "13938879795985597746"
        },
        {
          "file": "apps/lobay/ios/.gitignore",
          "hash": "11829594315324166477"
        },
        {
          "file": "apps/lobay/ios/Flutter/AppFrameworkInfo.plist",
          "hash": "7792689663883631766"
        },
        {
          "file": "apps/lobay/ios/Flutter/Debug.xcconfig",
          "hash": "12761441976492340084"
        },
        {
          "file": "apps/lobay/ios/Flutter/Release.xcconfig",
          "hash": "12761441976492340084"
        },
        {
          "file": "apps/lobay/ios/Runner.xcodeproj/project.pbxproj",
          "hash": "4397556178479812857"
        },
        {
          "file": "apps/lobay/ios/Runner.xcodeproj/project.xcworkspace/contents.xcworkspacedata",
          "hash": "7905627858604825927"
        },
        {
          "file": "apps/lobay/ios/Runner.xcodeproj/project.xcworkspace/xcshareddata/IDEWorkspaceChecks.plist",
          "hash": "12722229457274558422"
        },
        {
          "file": "apps/lobay/ios/Runner.xcodeproj/project.xcworkspace/xcshareddata/WorkspaceSettings.xcsettings",
          "hash": "11015238449633062087"
        },
        {
          "file": "apps/lobay/ios/Runner.xcodeproj/xcshareddata/xcschemes/Runner.xcscheme",
          "hash": "3723484679428227102"
        },
        {
          "file": "apps/lobay/ios/Runner.xcworkspace/contents.xcworkspacedata",
          "hash": "8566102419606845161"
        },
        {
          "file": "apps/lobay/ios/Runner.xcworkspace/xcshareddata/IDEWorkspaceChecks.plist",
          "hash": "12722229457274558422"
        },
        {
          "file": "apps/lobay/ios/Runner.xcworkspace/xcshareddata/WorkspaceSettings.xcsettings",
          "hash": "11015238449633062087"
        },
        {
          "file": "apps/lobay/ios/Runner/AppDelegate.swift",
          "hash": "10107173367169013511"
        },
        {
          "file": "apps/lobay/ios/Runner/Assets.xcassets/AppIcon.appiconset/Contents.json",
          "hash": "11701671655275461563"
        },
        {
          "file": "apps/lobay/ios/Runner/Assets.xcassets/AppIcon.appiconset/Icon-App-1024x1024@1x.png",
          "hash": "10744190497123437199"
        },
        {
          "file": "apps/lobay/ios/Runner/Assets.xcassets/AppIcon.appiconset/Icon-App-20x20@1x.png",
          "hash": "17857370851071422985"
        },
        {
          "file": "apps/lobay/ios/Runner/Assets.xcassets/AppIcon.appiconset/Icon-App-20x20@2x.png",
          "hash": "9089880720354936574"
        },
        {
          "file": "apps/lobay/ios/Runner/Assets.xcassets/AppIcon.appiconset/Icon-App-20x20@3x.png",
          "hash": "4153981484587230721"
        },
        {
          "file": "apps/lobay/ios/Runner/Assets.xcassets/AppIcon.appiconset/Icon-App-29x29@1x.png",
          "hash": "14233470423577647923"
        },
        {
          "file": "apps/lobay/ios/Runner/Assets.xcassets/AppIcon.appiconset/Icon-App-29x29@2x.png",
          "hash": "4256688772913297625"
        },
        {
          "file": "apps/lobay/ios/Runner/Assets.xcassets/AppIcon.appiconset/Icon-App-29x29@3x.png",
          "hash": "1725712220684977236"
        },
        {
          "file": "apps/lobay/ios/Runner/Assets.xcassets/AppIcon.appiconset/Icon-App-40x40@1x.png",
          "hash": "9089880720354936574"
        },
        {
          "file": "apps/lobay/ios/Runner/Assets.xcassets/AppIcon.appiconset/Icon-App-40x40@2x.png",
          "hash": "11020049274280637400"
        },
        {
          "file": "apps/lobay/ios/Runner/Assets.xcassets/AppIcon.appiconset/Icon-App-40x40@3x.png",
          "hash": "15597081444621038052"
        },
        {
          "file": "apps/lobay/ios/Runner/Assets.xcassets/AppIcon.appiconset/Icon-App-60x60@2x.png",
          "hash": "15597081444621038052"
        },
        {
          "file": "apps/lobay/ios/Runner/Assets.xcassets/AppIcon.appiconset/Icon-App-60x60@3x.png",
          "hash": "1874192408977113223"
        },
        {
          "file": "apps/lobay/ios/Runner/Assets.xcassets/AppIcon.appiconset/Icon-App-76x76@1x.png",
          "hash": "6391886343813779197"
        },
        {
          "file": "apps/lobay/ios/Runner/Assets.xcassets/AppIcon.appiconset/Icon-App-76x76@2x.png",
          "hash": "14420767294843778987"
        },
        {
          "file": "apps/lobay/ios/Runner/Assets.xcassets/AppIcon.appiconset/Icon-App-83.5x83.5@2x.png",
          "hash": "4764981302566026812"
        },
        {
          "file": "apps/lobay/ios/Runner/Assets.xcassets/LaunchImage.imageset/Contents.json",
          "hash": "9910583525975909610"
        },
        {
          "file": "apps/lobay/ios/Runner/Assets.xcassets/LaunchImage.imageset/LaunchImage.png",
          "hash": "8198580046434161737"
        },
        {
          "file": "apps/lobay/ios/Runner/Assets.xcassets/LaunchImage.imageset/LaunchImage@2x.png",
          "hash": "8198580046434161737"
        },
        {
          "file": "apps/lobay/ios/Runner/Assets.xcassets/LaunchImage.imageset/LaunchImage@3x.png",
          "hash": "8198580046434161737"
        },
        {
          "file": "apps/lobay/ios/Runner/Assets.xcassets/LaunchImage.imageset/README.md",
          "hash": "1692426015314638624"
        },
        {
          "file": "apps/lobay/ios/Runner/Base.lproj/LaunchScreen.storyboard",
          "hash": "10838346425801468425"
        },
        {
          "file": "apps/lobay/ios/Runner/Base.lproj/Main.storyboard",
          "hash": "8711865626386969945"
        },
        {
          "file": "apps/lobay/ios/Runner/Info.plist",
          "hash": "16836740517158814759"
        },
        {
          "file": "apps/lobay/ios/Runner/Runner-Bridging-Header.h",
          "hash": "9345155165121591741"
        },
        {
          "file": "apps/lobay/ios/RunnerTests/RunnerTests.swift",
          "hash": "6335546013279342170"
        },
        {
          "file": "apps/lobay/lib/main.dart",
          "hash": "9543316241186928113"
        },
        {
          "file": "apps/lobay/pubspec.lock",
          "hash": "9112920388235346046"
        },
        {
          "file": "apps/lobay/pubspec.yaml",
          "hash": "17958877555191966478"
        },
        {
          "file": "apps/lobay/test/widget_test.dart",
          "hash": "10986653475748964200"
        },
        {
          "file": "eslint.config.cjs",
          "hash": "4219588132382477313",
          "deps": [
            "npm:@nx/eslint-plugin"
          ]
        },
        {
          "file": "jest.config.ts",
          "hash": "3494843969422251966",
          "deps": [
            "npm:@nx/jest"
          ]
        },
        {
          "file": "jest.preset.js",
          "hash": "9430166341120122740",
          "deps": [
            "npm:@nx/jest"
          ]
        },
        {
          "file": "nx.json",
          "hash": "14601585190133103874"
        },
        {
          "file": "package-lock.json",
          "hash": "16944233821196672890"
        },
        {
          "file": "package.json",
          "hash": "9255146421957514001",
          "deps": [
            "npm:@eslint/js",
            "npm:@nx/eslint",
            "npm:@nx/eslint-plugin",
            "npm:@nx/express",
            "npm:@nx/jest",
            "npm:@nx/js",
            "npm:@nx/node",
            "npm:@nx/web",
            "npm:@nx/webpack",
            "npm:@nxrocks/nx-flutter",
            "npm:@pmmmwh/react-refresh-webpack-plugin",
            "npm:@svgr/webpack",
            "npm:@swc-node/register",
            "npm:@swc/core",
            "npm:@swc/helpers",
            "npm:@types/jest",
            "npm:@types/node",
            "npm:eslint",
            "npm:eslint-config-prettier",
            "npm:jest",
            "npm:jest-environment-node",
            "npm:nx",
            "npm:prettier",
            "npm:react-refresh",
            "npm:ts-jest",
            "npm:ts-node",
            "npm:tslib",
            "npm:typescript",
            "npm:typescript-eslint",
            "npm:webpack-cli",
            "npm:axios",
            "npm:express"
          ]
        },
        {
          "file": "tsconfig.base.json",
          "hash": "16936441711144470533"
        }
      ],
      "my-express-api-e2e": [
        {
          "file": "apps/my-express-api-e2e/eslint.config.cjs",
          "hash": "7759795430795630113"
        },
        {
          "file": "apps/my-express-api-e2e/jest.config.ts",
          "hash": "7741689681773748875"
        },
        {
          "file": "apps/my-express-api-e2e/project.json",
          "hash": "11462360534563815238"
        },
        {
          "file": "apps/my-express-api-e2e/src/my-express-api/my-express-api.spec.ts",
          "hash": "4579662685003779048",
          "deps": [
            "npm:axios"
          ]
        },
        {
          "file": "apps/my-express-api-e2e/src/support/global-setup.ts",
          "hash": "2568409276037275290"
        },
        {
          "file": "apps/my-express-api-e2e/src/support/global-teardown.ts",
          "hash": "5275447082211835490"
        },
        {
          "file": "apps/my-express-api-e2e/src/support/test-setup.ts",
          "hash": "15521797170623961900",
          "deps": [
            "npm:axios"
          ]
        },
        {
          "file": "apps/my-express-api-e2e/tsconfig.json",
          "hash": "15443990093475294480"
        },
        {
          "file": "apps/my-express-api-e2e/tsconfig.spec.json",
          "hash": "14954872453723519891"
        }
      ]
    }
  }
}